eduwallet/__init__.py
eduwallet/__main__.py
eduwallet-1.1.3.dist-info/METADATA
eduwallet-1.1.3.dist-info/WHEEL
eduwallet-1.1.3.dist-info/licenses/LICENSE
eduwallet-1.1.3.dist-info/RECORD
