Metadata-Version: 2.3
Name: eduwallet
Version: 1.1.3
Summary: A simple budget program
Project-URL: Homepage, https://github.com/pseudoisomer/eduwallet
Project-URL: Issues, https://github.com/pypa/sampleproject/issues
Author: kanade
License-File: LICENSE
Classifier: License :: OSI Approved :: MIT License
Classifier: Operating System :: OS Independent
Classifier: Programming Language :: Python :: 3
Requires-Python: >=3.8
